elektronn/__init__.py
elektronn/basisfunction_params.pkl
elektronn/ensemble_predict.py
elektronn/utils.py
elektronn/visualization_utils.py
elektronn/modelparams/04-20-33/hydra_training_kfold.log
elektronn/modelparams/04-20-33/model_fold_1.pth
elektronn/modelparams/04-20-33/model_fold_1_epoch_100.pth
elektronn/modelparams/04-20-33/model_fold_1_epoch_50.pth
elektronn/modelparams/04-20-33/model_fold_2.pth
elektronn/modelparams/04-20-33/model_fold_2_epoch_100.pth
elektronn/modelparams/04-20-33/model_fold_2_epoch_50.pth
elektronn/modelparams/04-20-33/model_fold_3.pth
elektronn/modelparams/04-20-33/model_fold_3_epoch_100.pth
elektronn/modelparams/04-20-33/model_fold_3_epoch_50.pth
elektronn/modelparams/04-20-33/model_fold_4.pth
elektronn/modelparams/04-20-33/model_fold_4_epoch_100.pth
elektronn/modelparams/04-20-33/model_fold_4_epoch_50.pth
elektronn/modelparams/04-20-33/model_fold_5.pth
elektronn/modelparams/04-20-33/model_fold_5_epoch_100.pth
elektronn/modelparams/04-20-33/model_fold_5_epoch_50.pth
elektronn/modelparams/04-20-33/.hydra/config.yaml
elektronn/modelparams/04-20-33/.hydra/hydra.yaml
elektronn/modelparams/04-20-33/.hydra/overrides.yaml
elektronn/modelparams/04-20-33/fold_indices/fold_1_indices.json
elektronn/modelparams/04-20-33/fold_indices/fold_2_indices.json
elektronn/modelparams/04-20-33/fold_indices/fold_3_indices.json
elektronn/modelparams/04-20-33/fold_indices/fold_4_indices.json
elektronn/modelparams/04-20-33/fold_indices/fold_5_indices.json
densus-0.1.1.dist-info/METADATA
densus-0.1.1.dist-info/WHEEL
densus-0.1.1.dist-info/top_level.txt
densus-0.1.1.dist-info/RECORD
