Metadata-Version: 2.4
Name: densus
Version: 0.1.1
Summary: Electron Density Neural Network for chemistry
Author-email: "Luis A. Kaermer" <you@email.com>
Requires-Dist: pickle-mixin
Requires-Dist: gdown
